notion_git_sync/__init__.py
notion_git_sync/converter.py
notion_git_sync/frontmatter.py
notion_git_sync/sync.py
notion_git_sync-0.1.6.dist-info/licenses/LICENSE
notion_git_sync-0.1.6.dist-info/METADATA
notion_git_sync-0.1.6.dist-info/WHEEL
notion_git_sync-0.1.6.dist-info/entry_points.txt
notion_git_sync-0.1.6.dist-info/top_level.txt
notion_git_sync-0.1.6.dist-info/RECORD
